hpc_pipeline_code/__init__.py
hpc_pipeline_code-0.0.1.dist-info/METADATA
hpc_pipeline_code-0.0.1.dist-info/WHEEL
hpc_pipeline_code-0.0.1.dist-info/top_level.txt
hpc_pipeline_code-0.0.1.dist-info/RECORD
